githuby/__init__.py
githuby/__main__.py
githuby/fetch.py
githuby/repository.py
githuby/user.py
githuby-0.1.1.dist-info/LICENSE
githuby-0.1.1.dist-info/WHEEL
githuby-0.1.1.dist-info/METADATA
githuby-0.1.1.dist-info/RECORD
