Metadata-Version: 2.1
Name: githuby
Version: 0.1.1
Summary: Simple package to get data about GitHub users
Home-page: https://github.com/chr3st5an/githuby
License: MIT
Keywords: github,api,asyncio,async,aiohttp,user
Author: Christian
Author-email: 64144555+chr3st5an@users.noreply.github.com
Requires-Python: >=3.8,<4.0
Classifier: Framework :: aiohttp
Classifier: License :: OSI Approved :: MIT License
Classifier: Natural Language :: English
Classifier: Operating System :: OS Independent
Classifier: Programming Language :: Python :: 3
Classifier: Programming Language :: Python :: 3.8
Classifier: Programming Language :: Python :: 3.9
Classifier: Programming Language :: Python :: 3.10
Classifier: Programming Language :: Python :: 3.11
Classifier: Programming Language :: Python :: 3.10
Classifier: Programming Language :: Python :: 3.8
Classifier: Programming Language :: Python :: 3.9
Requires-Dist: aiohttp (>=3.8.4,<4.0.0)
Project-URL: Bug Tracker, https://github.com/chr3st5an/githuby/issues
Project-URL: Repository, https://github.com/chr3st5an/githuby
